axonnexus_sdk/__init__.py
axonnexus_sdk/client.py
axonnexus_sdk-1.0.0.dist-info/licenses/LICENSE
axonnexus_sdk-1.0.0.dist-info/METADATA
axonnexus_sdk-1.0.0.dist-info/WHEEL
axonnexus_sdk-1.0.0.dist-info/top_level.txt
axonnexus_sdk-1.0.0.dist-info/RECORD
