Metadata-Version: 2.4
Name: axonnexus_sdk
Version: 1.0.0
Summary: A flexible Python SDK for the AxonNexus API on Hugging Face Spaces
Home-page: https://github.com/yourusername/axonnexus_sdk
Author: Atharv (Nubprogrammer)
Author-email: dev@axonnexus.ai
Project-URL: Discord Community, https://dsc.gg/axoninnova
Project-URL: Documentation, https://github.com/yourusername/axonnexus_sdk
Project-URL: Source Code, https://github.com/yourusername/axonnexus_sdk
Project-URL: Bug Tracker, https://github.com/yourusername/axonnexus_sdk/issues
Keywords: axonnexus api sdk huggingface
Classifier: Programming Language :: Python :: 3
Classifier: Programming Language :: Python :: 3.8
Classifier: Programming Language :: Python :: 3.9
Classifier: Programming Language :: Python :: 3.10
Classifier: Programming Language :: Python :: 3.11
Classifier: License :: OSI Approved :: MIT License
Classifier: Operating System :: OS Independent
Classifier: Development Status :: 5 - Production/Stable
Classifier: Intended Audience :: Developers
Classifier: Topic :: Software Development :: Libraries :: Python Modules
Classifier: Topic :: Internet
Classifier: Topic :: Utilities
Requires-Python: >=3.8
License-File: LICENSE
Requires-Dist: requests>=2.25.0
Dynamic: author
Dynamic: author-email
Dynamic: classifier
Dynamic: description
Dynamic: description-content-type
Dynamic: home-page
Dynamic: keywords
Dynamic: license-file
Dynamic: project-url
Dynamic: requires-dist
Dynamic: requires-python
Dynamic: summary
